quantumsim/__init__.py
quantumsim/_version.py
quantumsim/ansatz/__init__.py
quantumsim/ansatz/base.py
quantumsim/ansatz/custom_ansatz.py
quantumsim/ansatz/he_ansatz.py
quantumsim/ansatz/kupccgsd_ansatz.py
quantumsim/ansatz/uccds_ansatz.py
quantumsim/beginstate/__init__.py
quantumsim/beginstate/beginstate.py
quantumsim/lattice/__init__.py
quantumsim/lattice/lattice.py
quantumsim/optimizers/__init__.py
quantumsim/optimizers/adap_opt.py
quantumsim/optimizers/gradient_opt.py
quantumsim/optimizers/jax_opt.py
quantumsim/optimizers/scipy_opt.py
quantumsim/variational/__init__.py
quantumsim/variational/adapt/__init__.py
quantumsim/variational/adapt/base.py
quantumsim/variational/adapt/fermihubbard.py
quantumsim/variational/adapt/molecular.py
quantumsim/variational/struct/__init__.py
quantumsim/variational/struct/struct.py
quantumsim/variational/vqe/__init__.py
quantumsim/variational/vqe/base.py
quantumsim/variational/vqe/fermihubbard.py
quantumsim/variational/vqe/molecular.py
quantumsim/variational/vqe/spin.py
quantumsim/vqepy.egg-info/PKG-INFO
quantumsim/vqepy.egg-info/SOURCES.txt
quantumsim/vqepy.egg-info/dependency_links.txt
quantumsim/vqepy.egg-info/top_level.txt
vqepy-1.0.1.dist-info/LICENCE.txt
vqepy-1.0.1.dist-info/METADATA
vqepy-1.0.1.dist-info/WHEEL
vqepy-1.0.1.dist-info/top_level.txt
vqepy-1.0.1.dist-info/RECORD
