Metadata-Version: 2.1
Name: vqepy
Version: 1.0.1
Summary: An open source Python package for molecular and condensed matter VQE research
Project-URL: Source, https://github.com/javinoram/VqePy
Project-URL: website, https://github.com/javinoram/VqePy
Keywords: quantum chemistry,variational methods,condensed matter
Classifier: Programming Language :: Python :: 3
Classifier: License :: OSI Approved :: MIT License
Classifier: Operating System :: OS Independent
Requires-Python: >=3.10
License-File: LICENCE.txt
Requires-Dist: pyscf
Requires-Dist: numpy
Requires-Dist: scipy
Requires-Dist: pennylane
Requires-Dist: pandas
Requires-Dist: matplotlib
Requires-Dist: jax[cpu]
Requires-Dist: pennylane-qiskit
Requires-Dist: qiskit-ibm-provider
Requires-Dist: pyyaml
Requires-Dist: networkx
Requires-Dist: basis-set-exchange
Requires-Dist: ipykernel
Requires-Dist: pennylane-lightning
Requires-Dist: jaxopt
Requires-Dist: optax
